{"list":" text-muted bg-dark pb-2 pt-2 text-white align-items-center container d-flex justify-content-between d-md-inline-flex d-none flex-wrap p-1 navbar navbar-expand-lg navbar-light pb-3 pt-3 shadow-none d-inline-flex fw-bold h5 lh-1 mb-0 navbar-brand text-secondary text-uppercase me-1 navbar-toggler navbar-toggler-icon collapse navbar-collapse ms-auto navbar-nav nav-item active nav-link p-lg-3 btn btn-secondary ms-lg-3 hero-block pb-5 position-relative pt-5 text-white-50 bg-secondary col-12 col-lg-7 h-100 position-absolute start-0 top-0 gy-4 row col-lg-6 pb-4 display-3 lead mb-4 pe-sm-5 btn-info pe-4 ps-4 poster text-center pt-4 me-auto h1 mb-3 text-capitalize text-dark fw-light g-0 order-lg-2 p-3 img-fluid w-100 order-lg-1 ps-5 pe-5 h2 bg-info justify-content-center col-lg-4 col-md-6 py-3 bg-white bottom-0 end-0 me-3 ms-3 h4 small col-lg-3 col-sm-6 input-group form-control input-group-btn btn-primary rounded-end col-xl-4 link-info text-decoration-none col-sm-4 col-xl-2 text-info mb-2 list-unstyled border-secondary mt-0 mx-auto my-12 mx-0 text-grey ms-4 my-4 text-subtitle-1 mx-4 mb-1 px-4","map":{"text-muted":true,"bg-dark":true,"pb-2":true,"pt-2":true,"text-white":true,"align-items-center":true,"container":true,"d-flex":true,"justify-content-between":true,"d-md-inline-flex":true,"d-none":true,"flex-wrap":true,"p-1":true,"navbar":true,"navbar-expand-lg":true,"navbar-light":true,"pb-3":true,"pt-3":true,"shadow-none":true,"d-inline-flex":true,"fw-bold":true,"h5":true,"lh-1":true,"mb-0":true,"navbar-brand":true,"text-secondary":true,"text-uppercase":true,"me-1":true,"navbar-toggler":true,"navbar-toggler-icon":true,"collapse":true,"navbar-collapse":true,"ms-auto":true,"navbar-nav":true,"nav-item":true,"active":true,"nav-link":true,"p-lg-3":true,"btn":true,"btn-secondary":true,"ms-lg-3":true,"hero-block":true,"pb-5":true,"position-relative":true,"pt-5":true,"text-white-50":true,"bg-secondary":true,"col-12":true,"col-lg-7":true,"h-100":true,"position-absolute":true,"start-0":true,"top-0":true,"gy-4":true,"row":true,"col-lg-6":true,"pb-4":true,"display-3":true,"lead":true,"mb-4":true,"pe-sm-5":true,"btn-info":true,"pe-4":true,"ps-4":true,"poster":true,"text-center":true,"pt-4":true,"me-auto":true,"h1":true,"mb-3":true,"text-capitalize":true,"text-dark":true,"fw-light":true,"g-0":true,"order-lg-2":true,"p-3":true,"img-fluid":true,"w-100":true,"order-lg-1":true,"ps-5":true,"pe-5":true,"h2":true,"bg-info":true,"justify-content-center":true,"col-lg-4":true,"col-md-6":true,"py-3":true,"bg-white":true,"bottom-0":true,"end-0":true,"me-3":true,"ms-3":true,"h4":true,"small":true,"col-lg-3":true,"col-sm-6":true,"input-group":true,"form-control":true,"input-group-btn":true,"btn-primary":true,"rounded-end":true,"col-xl-4":true,"link-info":true,"text-decoration-none":true,"col-sm-4":true,"col-xl-2":true,"text-info":true,"mb-2":true,"list-unstyled":true,"border-secondary":true,"mt-0":true,"mx-auto":true,"my-12":true,"mx-0":true,"text-grey":true,"ms-4":true,"my-4":true,"text-subtitle-1":true,"mx-4":true,"mb-1":true,"px-4":true}}